cpmax_toolbox/__init__.py
cpmax_toolbox/analyzing.py
cpmax_toolbox/file_repair.py
cpmax_toolbox/vib_measurement.py
cpmax_toolbox-0.3.8.dist-info/METADATA
cpmax_toolbox-0.3.8.dist-info/WHEEL
cpmax_toolbox-0.3.8.dist-info/RECORD
